{"id": "apecoin", "symbol": "ape", "name": "APEcoin", "asset_platform_id": "binance-smart-chain", "platforms": {"binance-smart-chain": "0xa9ea4b786ee5b7a733c035564bfd9341a4c9fc1e"}, "block_time_in_minutes": 0, "hashing_algorithm": null, "categories": [], "public_notice": "Migrated from Ethereum (0x209c1808febf6c1ab7c65764bb61ad67d3923fcc) to BSC (0xa9eA4b786ee5b7A733c035564Bfd9341A4c9FC1e).", "additional_notices": ["Kindly be aware that liquidity provided in Automated Market Maker platforms (eg. Uniswap, Sushiswap, Balancer) can be removed (also known as rug pulling), resulting in a collapse of available liquidity. Please exercise caution when trading! This notice is NOT directed at any project in particular, and is more of a cautionary reminder for our users."], "localization": {"en": "APEcoin", "de": "APEcoin", "es": "APEcoin", "fr": "APEcoin", "it": "APEcoin", "pl": "APEcoin", "ro": "APEcoin", "hu": "APEcoin", "nl": "APEcoin", "pt": "APEcoin", "sv": "APEcoin", "vi": "APEcoin", "tr": "APEcoin", "ru": "APEcoin", "ja": "APEcoin", "zh": "APEcoin", "zh-tw": "APEcoin", "ko": "APEcoin", "ar": "APEcoin", "th": "APEcoin", "id": "APEcoin"}, "description": {"en": "", "de": "", "es": "", "fr": "", "it": "", "pl": "", "ro": "", "hu": "", "nl": "", "pt": "", "sv": "", "vi": "", "tr": "", "ru": "", "ja": "", "zh": "", "zh-tw": "", "ko": "", "ar": "", "th": "", "id": ""}, "links": {"homepage": ["https://apecoin.dev/", "", ""], "blockchain_site": ["https://bscscan.com/token/0xa9ea4b786ee5b7a733c035564bfd9341a4c9fc1e", "", "", "", ""], "official_forum_url": ["", "", ""], "chat_url": ["", "", ""], "announcement_url": ["https://discord.com/invite/2NnYMg6", ""], "twitter_screen_name": "go_apecoin", "facebook_username": "", "bitcointalk_thread_identifier": null, "telegram_channel_identifier": "APE_Token", "subreddit_url": null, "repos_url": {"github": [], "bitbucket": []}}, "image": {"thumb": "https://assets.coingecko.com/coins/images/12665/thumb/apecoin_logo.jpg?1601459267", "small": "https://assets.coingecko.com/coins/images/12665/small/apecoin_logo.jpg?1601459267", "large": "https://assets.coingecko.com/coins/images/12665/large/apecoin_logo.jpg?1601459267"}, "country_origin": "", "genesis_date": null, "contract_address": "0xa9ea4b786ee5b7a733c035564bfd9341a4c9fc1e", "sentiment_votes_up_percentage": 50.0, "sentiment_votes_down_percentage": 50.0, "market_cap_rank": null, "coingecko_rank": 5735, "coingecko_score": 1.678, "developer_score": 0.0, "community_score": 6.719, "liquidity_score": 1.0, "public_interest_score": 0.0, "market_data": {"current_price": {"aed": 0.300969, "ars": 7.72, "aud": 0.105651, "bch": 0.00010461, "bdt": 6.95, "bhd": 0.03089039, "bmd": 0.081941, "bnb": 0.0002176, "brl": 0.432863, "btc": 2.08e-06, "cad": 0.098934, "chf": 0.073442, "clp": 59.1, "cny": 0.527169, "czk": 1.71, "dkk": 0.498002, "dot": 0.00295921, "eos": 0.01315719, "eth": 3.022e-05, "eur": 0.066964, "gbp": 0.057724, "hkd": 0.636172, "huf": 23.39, "idr": 1176.28, "ils": 0.266449, "inr": 5.98, "jpy": 8.91, "krw": 92.32, "kwd": 0.0246318, "lkr": 16.14, "ltc": 0.00040988, "mmk": 134.81, "mxn": 1.63, "myr": 0.339237, "ngn": 33.8, "nok": 0.680622, "nzd": 0.114036, "php": 3.92, "pkr": 12.57, "pln": 0.301342, "rub": 6.02, "sar": 0.307292, "sek": 0.680285, "sgd": 0.109025, "thb": 2.57, "try": 0.686285, "twd": 2.29, "uah": 2.25, "usd": 0.081941, "vef": 0.00820478, "vnd": 1882.36, "xag": 0.00295657, "xau": 4.37e-05, "xdr": 0.056769, "xlm": 0.17521756, "xrp": 0.07445126, "yfi": 1.65e-06, "zar": 1.15, "bits": 2.08, "link": 0.00284994, "sats": 207.52}, "total_value_locked": null, "mcap_to_tvl_ratio": null, "fdv_to_tvl_ratio": null, "roi": null, "ath": {"aed": 5.86, "ars": 122.8, "aud": 2.23, "bch": 0.00725656, "bdt": 135.3, "bhd": 0.601889, "bmd": 1.6, "bnb": 0.05550696, "brl": 8.9, "btc": 0.00014888, "cad": 2.12, "chf": 1.46, "clp": 1274.79, "cny": 10.84, "czk": 36.67, "dkk": 10.08, "dot": 0.39272982, "eos": 0.63648016, "eth": 0.00455117, "eur": 1.36, "gbp": 1.23, "hkd": 12.37, "huf": 488.19, "idr": 23561, "ils": 5.45, "inr": 117.21, "jpy": 168.6, "krw": 1855.12, "kwd": 0.488611, "lkr": 293.82, "ltc": 0.0345433, "mmk": 2076.85, "mxn": 34.34, "myr": 6.63, "ngn": 402.75, "nok": 14.71, "nzd": 2.41, "php": 77.35, "pkr": 262.79, "pln": 6.08, "rub": 125.41, "sar": 5.99, "sek": 14.2, "sgd": 2.17, "thb": 49.86, "try": 12.39, "twd": 45.88, "uah": 45.19, "usd": 1.6, "vef": 396606, "vnd": 36951, "xag": 0.06582, "xau": 0.00083609, "xdr": 1.13, "xlm": 21.731415, "xrp": 6.281138, "yfi": 8.838e-05, "zar": 26.56, "bits": 27.85, "link": 0.17087397, "sats": 2785.1}, "ath_change_percentage": {"aed": -94.86602, "ars": -93.71113, "aud": -95.26503, "bch": -98.55836, "bdt": -94.86696, "bhd": -94.86776, "bmd": -94.86609, "bnb": -99.60798, "brl": -95.13587, "btc": -98.60617, "cad": -95.32804, "chf": -94.97116, "clp": -95.36424, "cny": -95.13599, "czk": -95.33987, "dkk": -95.06067, "dot": -99.2465, "eos": -97.93282, "eth": -99.33597, "eur": -95.05842, "gbp": -95.30382, "hkd": -94.857, "huf": -95.20803, "idr": -95.00743, "ils": -95.10661, "inr": -94.90058, "jpy": -94.71588, "krw": -95.02373, "kwd": -94.95881, "lkr": -94.50859, "ltc": -98.81344, "mmk": -93.50874, "mxn": -95.25144, "myr": -94.88647, "ngn": -91.60753, "nok": -95.37204, "nzd": -95.26019, "php": -94.92618, "pkr": -95.21725, "pln": -95.04775, "rub": -95.19566, "sar": -94.86716, "sek": -95.21046, "sgd": -94.97696, "thb": -94.84294, "try": -94.45942, "twd": -95.01171, "uah": -95.02038, "usd": -94.86609, "vef": -100.0, "vnd": -94.90583, "xag": -95.50812, "xau": -94.77386, "xdr": -94.98079, "xlm": -99.19371, "xrp": -98.81469, "yfi": -98.13561, "zar": -95.68723, "bits": -92.5491, "link": -98.33214, "sats": -92.5491}, "ath_date": {"aed": "2020-10-06T07:55:12.321Z", "ars": "2020-10-06T07:55:12.321Z", "aud": "2020-10-06T07:55:12.321Z", "bch": "2020-10-06T08:06:10.895Z", "bdt": "2020-10-06T07:55:12.321Z", "bhd": "2020-10-06T07:55:12.321Z", "bmd": "2020-10-06T07:55:12.321Z", "bnb": "2020-10-06T08:06:10.895Z", "brl": "2020-10-06T07:55:12.321Z", "btc": "2020-10-06T07:55:12.321Z", "cad": "2020-10-06T07:55:12.321Z", "chf": "2020-10-06T07:55:12.321Z", "clp": "2020-10-06T07:55:12.321Z", "cny": "2020-10-06T07:55:12.321Z", "czk": "2020-10-06T07:55:12.321Z", "dkk": "2020-10-06T07:55:12.321Z", "dot": "2020-10-06T07:55:12.321Z", "eos": "2020-10-06T08:06:10.895Z", "eth": "2020-10-06T08:06:10.895Z", "eur": "2020-10-06T07:55:12.321Z", "gbp": "2020-10-06T07:55:12.321Z", "hkd": "2020-10-06T07:55:12.321Z", "huf": "2020-10-06T07:55:12.321Z", "idr": "2020-10-06T07:55:12.321Z", "ils": "2020-10-06T07:55:12.321Z", "inr": "2020-10-06T07:55:12.321Z", "jpy": "2020-10-06T07:55:12.321Z", "krw": "2020-10-06T07:55:12.321Z", "kwd": "2020-10-06T07:55:12.321Z", "lkr": "2020-10-06T07:55:12.321Z", "ltc": "2020-10-06T07:55:12.321Z", "mmk": "2020-10-06T07:55:12.321Z", "mxn": "2020-10-06T07:55:12.321Z", "myr": "2020-10-06T07:55:12.321Z", "ngn": "2021-03-12T19:20:25.966Z", "nok": "2020-10-06T08:06:10.895Z", "nzd": "2020-10-06T07:55:12.321Z", "php": "2020-10-06T07:55:12.321Z", "pkr": "2020-10-06T07:55:12.321Z", "pln": "2020-10-06T08:06:10.895Z", "rub": "2020-10-06T08:06:10.895Z", "sar": "2020-10-06T07:55:12.321Z", "sek": "2020-10-06T07:55:12.321Z", "sgd": "2020-10-06T07:55:12.321Z", "thb": "2020-10-06T07:55:12.321Z", "try": "2020-10-06T07:55:12.321Z", "twd": "2020-10-06T07:55:12.321Z", "uah": "2020-10-06T07:55:12.321Z", "usd": "2020-10-06T07:55:12.321Z", "vef": "2020-10-06T07:55:12.321Z", "vnd": "2020-10-06T07:55:12.321Z", "xag": "2020-10-06T07:55:12.321Z", "xau": "2020-10-06T07:55:12.321Z", "xdr": "2020-10-06T07:55:12.321Z", "xlm": "2020-10-06T08:06:10.895Z", "xrp": "2020-10-06T08:06:10.895Z", "yfi": "2020-10-06T08:06:10.895Z", "zar": "2020-10-06T07:55:12.321Z", "bits": "2020-12-18T21:46:25.805Z", "link": "2020-10-06T08:06:10.895Z", "sats": "2020-12-18T21:46:25.805Z"}, "atl": {"aed": 0.01741722, "ars": 0.427854, "aud": 0.00608959, "bch": 9.21e-06, "bdt": 0.402105, "bhd": 0.00178833, "bmd": 0.00474185, "bnb": 1.96e-05, "brl": 0.02664728, "btc": 9.68e-08, "cad": 0.00599885, "chf": 0.00437414, "clp": 3.45, "cny": 0.03068116, "czk": 0.103249, "dkk": 0.02929628, "dot": 0.00013032, "eos": 0.00124874, "eth": 3.06e-06, "eur": 0.00393974, "gbp": 0.00340278, "hkd": 0.03678693, "huf": 1.44, "idr": 67.69, "ils": 0.01571167, "inr": 0.345356, "jpy": 0.508639, "krw": 5.33, "kwd": 0.0014351, "lkr": 0.927077, "ltc": 2.573e-05, "mmk": 6.69, "mxn": 0.099082, "myr": 0.01923293, "ngn": 1.81, "nok": 0.04037501, "nzd": 0.00653619, "php": 0.230207, "pkr": 0.744653, "pln": 0.01793449, "rub": 0.350181, "sar": 0.01778779, "sek": 0.04003441, "sgd": 0.00631863, "thb": 0.143897, "try": 0.03544719, "twd": 0.132052, "uah": 0.13193, "usd": 0.00474185, "vef": 0.0004748, "vnd": 109.42, "xag": 0.00018345, "xau": 2.77e-06, "xdr": 0.00330107, "xlm": 0.0114215, "xrp": 0.01047755, "yfi": 1.423e-07, "zar": 0.071464, "bits": 0.096818, "link": 0.00016301, "sats": 9.68}, "atl_change_percentage": {"aed": 1627.99854, "ars": 1704.95009, "aud": 1634.95213, "bch": 1035.30484, "bdt": 1627.18212, "bhd": 1627.33631, "bmd": 1628.04652, "bnb": 1010.02591, "brl": 1524.41785, "btc": 2043.34847, "cad": 1549.2216, "chf": 1578.99945, "clp": 1612.84528, "cny": 1618.21821, "czk": 1554.95066, "dkk": 1599.88227, "dot": 2170.80005, "eos": 953.63546, "eth": 887.46763, "eur": 1599.70626, "gbp": 1596.36598, "hkd": 1629.34179, "huf": 1528.38637, "idr": 1637.62122, "ils": 1595.86804, "inr": 1630.68146, "jpy": 1651.49451, "krw": 1630.62719, "kwd": 1616.38141, "lkr": 1640.41844, "ltc": 1492.81111, "mmk": 1916.17651, "mxn": 1545.81985, "myr": 1663.83447, "ngn": 1769.68968, "nok": 1585.75001, "nzd": 1644.67876, "php": 1604.79926, "pkr": 1587.87213, "pln": 1580.23687, "rub": 1620.52351, "sar": 1627.54256, "sek": 1599.25028, "sgd": 1625.45936, "thb": 1686.87709, "try": 1836.07742, "twd": 1633.02927, "uah": 1605.61934, "usd": 1628.04652, "vef": 1628.04652, "vnd": 1620.29838, "xag": 1511.66962, "xau": 1477.09495, "xdr": 1619.7086, "xlm": 1434.10321, "xrp": 610.57917, "yfi": 1058.14701, "zar": 1503.02996, "bits": 2043.34847, "link": 1648.35822, "sats": 2043.34847}, "atl_date": {"aed": "2021-03-04T09:43:20.784Z", "ars": "2021-03-04T09:43:20.784Z", "aud": "2021-03-04T09:43:20.784Z", "bch": "2021-03-04T09:43:20.784Z", "bdt": "2021-03-04T09:43:20.784Z", "bhd": "2021-03-04T09:43:20.784Z", "bmd": "2021-03-04T09:43:20.784Z", "bnb": "2021-03-04T09:52:35.861Z", "brl": "2021-03-04T09:43:20.784Z", "btc": "2021-03-04T09:43:20.784Z", "cad": "2021-03-04T09:43:20.784Z", "chf": "2021-03-04T09:43:20.784Z", "clp": "2021-03-04T09:43:20.784Z", "cny": "2021-03-04T09:43:20.784Z", "czk": "2021-03-04T09:43:20.784Z", "dkk": "2021-03-04T09:43:20.784Z", "dot": "2021-03-04T09:43:20.784Z", "eos": "2021-03-04T09:52:35.861Z", "eth": "2021-03-04T09:52:35.861Z", "eur": "2021-03-04T09:43:20.784Z", "gbp": "2021-03-04T09:43:20.784Z", "hkd": "2021-03-04T09:43:20.784Z", "huf": "2021-03-04T09:43:20.784Z", "idr": "2021-03-04T09:43:20.784Z", "ils": "2021-03-04T09:43:20.784Z", "inr": "2021-03-04T09:43:20.784Z", "jpy": "2021-03-04T09:43:20.784Z", "krw": "2021-03-04T09:43:20.784Z", "kwd": "2021-03-04T09:43:20.784Z", "lkr": "2021-03-04T09:43:20.784Z", "ltc": "2021-03-04T09:52:35.861Z", "mmk": "2021-03-04T09:43:20.784Z", "mxn": "2021-03-04T09:43:20.784Z", "myr": "2021-03-04T09:43:20.784Z", "ngn": "2021-03-04T09:43:20.784Z", "nok": "2021-03-04T09:43:20.784Z", "nzd": "2021-03-04T09:43:20.784Z", "php": "2021-03-04T09:43:20.784Z", "pkr": "2021-03-04T09:43:20.784Z", "pln": "2021-03-04T09:43:20.784Z", "rub": "2021-03-04T09:43:20.784Z", "sar": "2021-03-04T09:43:20.784Z", "sek": "2021-03-04T09:43:20.784Z", "sgd": "2021-03-04T09:43:20.784Z", "thb": "2021-03-04T09:43:20.784Z", "try": "2021-03-04T09:43:20.784Z", "twd": "2021-03-04T09:43:20.784Z", "uah": "2021-03-04T09:43:20.784Z", "usd": "2021-03-04T09:43:20.784Z", "vef": "2021-03-04T09:43:20.784Z", "vnd": "2021-03-04T09:43:20.784Z", "xag": "2021-03-04T09:43:20.784Z", "xau": "2021-03-04T09:43:20.784Z", "xdr": "2021-03-04T09:43:20.784Z", "xlm": "2021-03-04T09:43:20.784Z", "xrp": "2021-03-04T09:43:20.784Z", "yfi": "2021-03-04T09:43:20.784Z", "zar": "2021-03-04T09:43:20.784Z", "bits": "2021-03-04T09:43:20.784Z", "link": "2021-03-04T09:43:20.784Z", "sats": "2021-03-04T09:43:20.784Z"}, "market_cap": {"aed": 0.0, "ars": 0.0, "aud": 0.0, "bch": 0.0, "bdt": 0.0, "bhd": 0.0, "bmd": 0.0, "bnb": 0.0, "brl": 0.0, "btc": 0.0, "cad": 0.0, "chf": 0.0, "clp": 0.0, "cny": 0.0, "czk": 0.0, "dkk": 0.0, "dot": 0.0, "eos": 0.0, "eth": 0.0, "eur": 0.0, "gbp": 0.0, "hkd": 0.0, "huf": 0.0, "idr": 0.0, "ils": 0.0, "inr": 0.0, "jpy": 0.0, "krw": 0.0, "kwd": 0.0, "lkr": 0.0, "ltc": 0.0, "mmk": 0.0, "mxn": 0.0, "myr": 0.0, "ngn": 0.0, "nok": 0.0, "nzd": 0.0, "php": 0.0, "pkr": 0.0, "pln": 0.0, "rub": 0.0, "sar": 0.0, "sek": 0.0, "sgd": 0.0, "thb": 0.0, "try": 0.0, "twd": 0.0, "uah": 0.0, "usd": 0.0, "vef": 0.0, "vnd": 0.0, "xag": 0.0, "xau": 0.0, "xdr": 0.0, "xlm": 0.0, "xrp": 0.0, "yfi": 0.0, "zar": 0.0, "bits": 0.0, "link": 0.0, "sats": 0.0}, "market_cap_rank": null, "fully_diluted_valuation": {}, "total_volume": {"aed": 14374.44, "ars": 368833, "aud": 5045.96, "bch": 4.99638, "bdt": 331701, "bhd": 1475.34, "bmd": 3913.56, "bnb": 10.392587, "brl": 20674, "btc": 0.09911033, "cad": 4725.15, "chf": 3507.61, "clp": 2822457, "cny": 25178, "czk": 81609, "dkk": 23785, "dot": 141.333, "eos": 628.394, "eth": 1.443377, "eur": 3198.23, "gbp": 2756.91, "hkd": 30384, "huf": 1117313, "idr": 56179687, "ils": 12725.75, "inr": 285465, "jpy": 425488, "krw": 4409051, "kwd": 1176.43, "lkr": 770616, "ltc": 19.57596, "mmk": 6438760, "mxn": 77883, "myr": 16202.12, "ngn": 1614342, "nok": 32507, "nzd": 5446.39, "php": 187439, "pkr": 600292, "pln": 14392.24, "rub": 287754, "sar": 14676.4, "sek": 32491, "sgd": 5207.1, "thb": 122805, "try": 32777, "twd": 109300, "uah": 107472, "usd": 3913.56, "vef": 391.86, "vnd": 89902388, "xag": 141.21, "xau": 2.09, "xdr": 2711.31, "xlm": 8368, "xrp": 3556, "yfi": 0.07869996, "zar": 54714, "bits": 99110, "link": 136.114, "sats": 9911033}, "high_24h": {"aed": 0.331637, "ars": 8.51, "aud": 0.116279, "bch": 0.00010649, "bdt": 7.65, "bhd": 0.03403352, "bmd": 0.090286, "bnb": 0.00022018, "brl": 0.477773, "btc": 2.16e-06, "cad": 0.108943, "chf": 0.081236, "clp": 64.51, "cny": 0.580834, "czk": 1.88, "dkk": 0.549722, "dot": 0.00300482, "eos": 0.01331938, "eth": 3.079e-05, "eur": 0.073927, "gbp": 0.063812, "hkd": 0.700955, "huf": 25.84, "idr": 1297.31, "ils": 0.294103, "inr": 6.6, "jpy": 9.83, "krw": 101.91, "kwd": 0.02714988, "lkr": 17.78, "ltc": 0.00040953, "mmk": 148.54, "mxn": 1.8, "myr": 0.373602, "ngn": 37.24, "nok": 0.750789, "nzd": 0.125329, "php": 4.32, "pkr": 13.85, "pln": 0.33242, "rub": 6.64, "sar": 0.338591, "sek": 0.751474, "sgd": 0.120154, "thb": 2.83, "try": 0.755411, "twd": 2.52, "uah": 2.48, "usd": 0.090286, "vef": 0.0090403, "vnd": 2077.86, "xag": 0.00325003, "xau": 4.811e-05, "xdr": 0.062558, "xlm": 0.174527, "xrp": 0.07363538, "yfi": 1.66e-06, "zar": 1.26, "bits": 2.16, "link": 0.00283066, "sats": 215.63}, "low_24h": {"aed": 0.272947, "ars": 7.0, "aud": 0.096014, "bch": 9.406e-05, "bdt": 6.3, "bhd": 0.02801578, "bmd": 0.074308, "bnb": 0.00020373, "brl": 0.394574, "btc": 1.9e-06, "cad": 0.090206, "chf": 0.066994, "clp": 53.14, "cny": 0.478489, "czk": 1.55, "dkk": 0.453434, "dot": 0.00267005, "eos": 0.01189694, "eth": 2.779e-05, "eur": 0.060979, "gbp": 0.052669, "hkd": 0.57678, "huf": 21.35, "idr": 1070.14, "ils": 0.242454, "inr": 5.43, "jpy": 8.1, "krw": 84.13, "kwd": 0.02235591, "lkr": 14.64, "ltc": 0.00035746, "mmk": 122.34, "mxn": 1.48, "myr": 0.308028, "ngn": 30.65, "nok": 0.619474, "nzd": 0.103597, "php": 3.56, "pkr": 11.38, "pln": 0.275583, "rub": 5.47, "sar": 0.278716, "sek": 0.620815, "sgd": 0.099097, "thb": 2.33, "try": 0.623141, "twd": 2.08, "uah": 2.04, "usd": 0.074308, "vef": 0.00744043, "vnd": 1715.47, "xag": 0.00268807, "xau": 3.975e-05, "xdr": 0.051475, "xlm": 0.15457606, "xrp": 0.06391627, "yfi": 1.46e-06, "zar": 1.05, "bits": 1.9, "link": 0.00253888, "sats": 189.66}, "price_change_24h": 0.00717664, "price_change_percentage_24h": 9.59898, "price_change_percentage_7d": -48.40153, "price_change_percentage_14d": -49.79745, "price_change_percentage_30d": -48.98219, "price_change_percentage_60d": -70.76529, "price_change_percentage_200d": -59.1933, "price_change_percentage_1y": 0.0, "market_cap_change_24h": 0.0, "market_cap_change_percentage_24h": 0.0, "price_change_24h_in_currency": {"aed": 0.02635972, "ars": 0.680161, "aud": 0.00920337, "bch": 7.24e-06, "bdt": 0.603829, "bhd": 0.00270225, "bmd": 0.00717664, "bnb": 8.23e-06, "brl": 0.03587774, "btc": 1.786e-07, "cad": 0.00842793, "chf": 0.0058629, "clp": 5.63, "cny": 0.04571487, "czk": 0.146768, "dkk": 0.04189084, "dot": 0.00017836, "eos": 0.00091977, "eth": 1.71e-06, "eur": 0.00562228, "gbp": 0.00479235, "hkd": 0.055665, "huf": 1.91, "idr": 101.2, "ils": 0.02281801, "inr": 0.510847, "jpy": 0.750063, "krw": 7.65, "kwd": 0.0021402, "lkr": 1.4, "ltc": 3.82e-05, "mmk": 11.72, "mxn": 0.143934, "myr": 0.0297113, "ngn": 2.96, "nok": 0.061148, "nzd": 0.01002456, "php": 0.343679, "pkr": 1.11, "pln": 0.02391981, "rub": 0.516765, "sar": 0.02686716, "sek": 0.057159, "sgd": 0.00936669, "thb": 0.225896, "try": 0.060819, "twd": 0.19668, "uah": 0.198382, "usd": 0.00717664, "vef": 0.0007186, "vnd": 156.74, "xag": 0.0002685, "xau": 3.81e-06, "xdr": 0.00497683, "xlm": 0.01749661, "xrp": 0.00876751, "yfi": 1.368e-07, "zar": 0.094186, "bits": 0.178585, "link": 0.00019167, "sats": 17.86}, "price_change_percentage_1h_in_currency": {"aed": -1.17579, "ars": -1.18223, "aud": -1.19893, "bch": 1.5233, "bdt": -1.17579, "bhd": -1.17552, "bmd": -1.17579, "bnb": 1.91898, "brl": -1.17766, "btc": 0.0, "cad": -1.1766, "chf": -1.21183, "clp": -1.17569, "cny": -1.17271, "czk": -1.18384, "dkk": -1.20191, "dot": 1.95271, "eos": 1.39824, "eth": 1.11463, "eur": -1.199, "gbp": -1.24294, "hkd": -1.17069, "huf": -1.22256, "idr": -1.23936, "ils": -1.12412, "inr": -1.19604, "jpy": -1.18442, "krw": -1.16566, "kwd": -1.1748, "lkr": -1.17579, "ltc": 0.79006, "mmk": -1.17579, "mxn": -1.24112, "myr": -1.17579, "ngn": -1.17579, "nok": -1.1923, "nzd": -1.19765, "php": -1.1932, "pkr": -1.17579, "pln": -1.16732, "rub": -1.19782, "sar": -1.1747, "sek": -1.21031, "sgd": -1.21588, "thb": -1.20937, "try": -1.30394, "twd": -1.21364, "uah": -1.17579, "usd": -1.17579, "vef": -1.17579, "vnd": -1.19849, "xag": -0.99752, "xau": -1.16281, "xdr": -1.17579, "xlm": 0.89944, "xrp": 1.61328, "yfi": 0.99211, "zar": -1.29036, "bits": 0.0, "link": 1.98132, "sats": 0.0}, "price_change_percentage_24h_in_currency": {"aed": 9.59898, "ars": 9.65809, "aud": 9.54231, "bch": 7.43096, "bdt": 9.52223, "bhd": 9.58648, "bmd": 9.59898, "bnb": 3.93084, "brl": 9.03755, "btc": 9.4162, "cad": 9.31198, "chf": 8.67564, "clp": 10.53384, "cny": 9.49516, "czk": 9.39649, "dkk": 9.18434, "dot": 6.41404, "eos": 7.51607, "eth": 5.98632, "eur": 9.16551, "gbp": 9.0539, "hkd": 9.5891, "huf": 8.89497, "idr": 9.413, "ils": 9.3658, "inr": 9.34564, "jpy": 9.19339, "krw": 9.03695, "kwd": 9.51555, "lkr": 9.52126, "ltc": 10.27694, "mmk": 9.52139, "mxn": 9.68099, "myr": 9.59898, "ngn": 9.59898, "nok": 9.87092, "nzd": 9.63798, "php": 9.59758, "pkr": 9.73117, "pln": 8.62217, "rub": 9.38178, "sar": 9.58089, "sek": 9.17289, "sgd": 9.39877, "thb": 9.63158, "try": 9.72376, "twd": 9.40233, "uah": 9.66847, "usd": 9.59898, "vef": 9.59898, "vnd": 9.0831, "xag": 9.98849, "xau": 9.54967, "xdr": 9.60926, "xlm": 11.0934, "xrp": 13.34807, "yfi": 9.0565, "zar": 8.95804, "bits": 9.4162, "link": 7.21036, "sats": 9.4162}, "price_change_percentage_7d_in_currency": {"aed": -48.40228, "ars": -48.27452, "aud": -48.58274, "bch": -19.82069, "bdt": -48.38649, "bhd": -48.4003, "bmd": -48.40153, "bnb": -23.07687, "brl": -48.62848, "btc": -35.69879, "cad": -48.7759, "chf": -48.95562, "clp": -47.42596, "cny": -48.54948, "czk": -49.02463, "dkk": -49.06472, "dot": -24.88851, "eos": -15.81232, "eth": -29.03262, "eur": -49.0647, "gbp": -48.92759, "hkd": -48.43104, "huf": -50.13676, "idr": -48.24084, "ils": -48.94857, "inr": -48.7611, "jpy": -48.76038, "krw": -48.4272, "kwd": -48.47935, "lkr": -48.41435, "ltc": -21.08661, "mmk": -45.48304, "mxn": -48.50466, "myr": -48.22018, "ngn": -47.91436, "nok": -48.71128, "nzd": -48.40265, "php": -48.34373, "pkr": -47.94064, "pln": -49.36997, "rub": -48.74877, "sar": -48.4047, "sek": -49.02736, "sgd": -48.51916, "thb": -48.31775, "try": -49.17702, "twd": -48.45645, "uah": -48.71015, "usd": -48.40153, "vef": -48.40153, "vnd": -48.56362, "xag": -49.5614, "xau": -49.74451, "xdr": -48.65478, "xlm": -29.72673, "xrp": -39.25742, "yfi": -31.97283, "zar": -48.91098, "bits": -35.69879, "link": -23.95978, "sats": -35.69879}, "price_change_percentage_14d_in_currency": {"aed": -49.7974, "ars": -49.49354, "aud": -49.92833, "bch": -12.10021, "bdt": -49.82384, "bhd": -49.79905, "bmd": -49.79745, "bnb": -13.83353, "brl": -50.4688, "btc": -27.45619, "cad": -50.57773, "chf": -50.75632, "clp": -48.65111, "cny": -50.15847, "czk": -51.27897, "dkk": -50.73011, "dot": -28.77303, "eos": -26.19048, "eth": -35.85727, "eur": -50.7367, "gbp": -50.81467, "hkd": -49.82971, "huf": -52.05576, "idr": -49.72706, "ils": -49.99301, "inr": -50.49578, "jpy": -50.07112, "krw": -49.76864, "kwd": -49.92805, "lkr": -49.82533, "ltc": -14.4976, "mmk": -46.97434, "mxn": -50.69133, "myr": -49.6149, "ngn": -45.57543, "nok": -50.08176, "nzd": -49.61462, "php": -49.9011, "pkr": -49.63033, "pln": -51.59784, "rub": -50.68513, "sar": -49.80097, "sek": -50.9057, "sgd": -50.0235, "thb": -49.49766, "try": -49.54149, "twd": -49.89201, "uah": -50.26542, "usd": -49.79745, "vef": -49.79745, "vnd": -50.02255, "xag": -51.91062, "xau": -52.06971, "xdr": -50.18937, "xlm": -32.31033, "xrp": -22.74618, "yfi": -45.28864, "zar": -51.15186, "bits": -27.45619, "link": -16.65302, "sats": -27.45619}, "price_change_percentage_30d_in_currency": {"aed": -48.98515, "ars": -48.29392, "aud": -49.1987, "bch": -37.8104, "bdt": -48.99288, "bhd": -48.98544, "bmd": -48.98219, "bnb": -21.57736, "brl": -51.60764, "btc": -26.99757, "cad": -51.17201, "chf": -50.08718, "clp": -47.21073, "cny": -49.50026, "czk": -50.64601, "dkk": -49.83412, "dot": -34.8476, "eos": -44.93844, "eth": -56.13096, "eur": -49.8364, "gbp": -49.91995, "hkd": -48.96773, "huf": -51.48059, "idr": -49.64205, "ils": -48.95097, "inr": -50.67726, "jpy": -48.69339, "krw": -48.48789, "kwd": -49.09329, "lkr": -48.11917, "ltc": -32.627, "mmk": -40.45686, "mxn": -49.14253, "myr": -48.67224, "ngn": -44.76419, "nok": -49.31752, "nzd": -49.12845, "php": -49.43916, "pkr": -48.81945, "pln": -50.41171, "rub": -51.19296, "sar": -48.9852, "sek": -49.81474, "sgd": -48.93114, "thb": -48.81994, "try": -47.34897, "twd": -49.18669, "uah": -49.9796, "usd": -48.98219, "vef": -48.98219, "vnd": -49.28128, "xag": -52.53403, "xau": -51.66004, "xdr": -49.36495, "xlm": -42.52606, "xrp": -35.7921, "yfi": -49.44096, "zar": -50.13469, "bits": -26.99757, "link": -30.62827, "sats": -26.99757}, "price_change_percentage_60d_in_currency": {"aed": -70.76699, "ars": -69.83176, "aud": -70.88209, "bch": -80.38023, "bdt": -70.75769, "bhd": -70.80185, "bmd": -70.76529, "bnb": -79.43325, "brl": -71.87915, "btc": -57.27307, "cad": -71.8107, "chf": -71.82341, "clp": -70.4415, "cny": -71.10439, "czk": -72.21776, "dkk": -71.60218, "dot": -61.17342, "eos": -80.43184, "eth": -80.71013, "eur": -71.6053, "gbp": -71.50804, "hkd": -70.77173, "huf": -73.05492, "idr": -70.87629, "ils": -71.20097, "inr": -70.5513, "jpy": -70.81509, "krw": -70.83959, "kwd": -70.92238, "lkr": -70.88185, "ltc": -71.36805, "mmk": -65.92155, "mxn": -71.85137, "myr": -70.53398, "ngn": -70.65592, "nok": -71.63006, "nzd": -70.89831, "php": -71.18203, "pkr": -71.22246, "pln": -72.35529, "rub": -71.05625, "sar": -70.77119, "sek": -71.63715, "sgd": -71.06281, "thb": -70.26546, "try": -69.78918, "twd": -71.24812, "uah": -71.07865, "usd": -70.76529, "vef": -70.76529, "vnd": -70.93341, "xag": -72.70777, "xau": -72.89223, "xdr": -71.05661, "xlm": -74.69852, "xrp": -86.1946, "yfi": -79.16775, "zar": -72.41525, "bits": -57.27307, "link": -70.22193, "sats": -57.27307}, "price_change_percentage_200d_in_currency": {"aed": -59.19315, "ars": -50.91994, "aud": -63.10022, "bch": -86.06796, "bdt": -59.24368, "bhd": -59.19904, "bmd": -59.1933, "bnb": -96.93177, "brl": -62.46559, "btc": -85.84491, "cad": -63.10706, "chf": -60.11548, "clp": -61.94258, "cny": -60.77076, "czk": -63.65827, "dkk": -61.21057, "dot": -93.82929, "eos": -83.54539, "eth": -94.06577, "eur": -61.16716, "gbp": -62.84421, "hkd": -59.13509, "huf": -62.99731, "idr": -59.9624, "ils": -61.04813, "inr": -60.11892, "jpy": -57.60143, "krw": -59.55393, "kwd": -59.84912, "lkr": -56.40038, "ltc": -88.70102, "mmk": -47.82623, "mxn": -61.81267, "myr": -59.32349, "ngn": -55.75908, "nok": -64.55701, "nzd": -62.52168, "php": -59.74876, "pkr": -60.98942, "pln": -62.07034, "rub": -62.242, "sar": -59.1961, "sek": -62.01071, "sgd": -60.26744, "thb": -58.92499, "try": -59.15392, "twd": -60.1497, "uah": -60.62527, "usd": -59.1933, "vef": -99.99998, "vnd": -59.65783, "xag": -65.35878, "xau": -59.14733, "xdr": -60.0824, "xlm": -93.15055, "xrp": -91.13005, "yfi": -91.27966, "zar": -64.90098, "bits": -85.84491, "link": -83.63095, "sats": -85.84491}, "price_change_percentage_1y_in_currency": {}, "market_cap_change_24h_in_currency": {"aed": 0.0, "ars": 0.0, "aud": 0.0, "bch": 0.0, "bdt": 0.0, "bhd": 0.0, "bmd": 0.0, "bnb": 0.0, "brl": 0.0, "btc": 0.0, "cad": 0.0, "chf": 0.0, "clp": 0.0, "cny": 0.0, "czk": 0.0, "dkk": 0.0, "dot": 0.0, "eos": 0.0, "eth": 0.0, "eur": 0.0, "gbp": 0.0, "hkd": 0.0, "huf": 0.0, "idr": 0.0, "ils": 0.0, "inr": 0.0, "jpy": 0.0, "krw": 0.0, "kwd": 0.0, "lkr": 0.0, "ltc": 0.0, "mmk": 0.0, "mxn": 0.0, "myr": 0.0, "ngn": 0.0, "nok": 0.0, "nzd": 0.0, "php": 0.0, "pkr": 0.0, "pln": 0.0, "rub": 0.0, "sar": 0.0, "sek": 0.0, "sgd": 0.0, "thb": 0.0, "try": 0.0, "twd": 0.0, "uah": 0.0, "usd": 0.0, "vef": 0.0, "vnd": 0.0, "xag": 0.0, "xau": 0.0, "xdr": 0.0, "xlm": 0.0, "xrp": 0.0, "yfi": 0.0, "zar": 0.0, "bits": 0.0, "link": 0.0, "sats": 0.0}, "market_cap_change_percentage_24h_in_currency": {"aed": 0.0, "ars": 0.0, "aud": 0.0, "bch": 0.0, "bdt": 0.0, "bhd": 0.0, "bmd": 0.0, "bnb": 0.0, "brl": 0.0, "btc": 0.0, "cad": 0.0, "chf": 0.0, "clp": 0.0, "cny": 0.0, "czk": 0.0, "dkk": 0.0, "dot": 0.0, "eos": 0.0, "eth": 0.0, "eur": 0.0, "gbp": 0.0, "hkd": 0.0, "huf": 0.0, "idr": 0.0, "ils": 0.0, "inr": 0.0, "jpy": 0.0, "krw": 0.0, "kwd": 0.0, "lkr": 0.0, "ltc": 0.0, "mmk": 0.0, "mxn": 0.0, "myr": 0.0, "ngn": 0.0, "nok": 0.0, "nzd": 0.0, "php": 0.0, "pkr": 0.0, "pln": 0.0, "rub": 0.0, "sar": 0.0, "sek": 0.0, "sgd": 0.0, "thb": 0.0, "try": 0.0, "twd": 0.0, "uah": 0.0, "usd": 0.0, "vef": 0.0, "vnd": 0.0, "xag": 0.0, "xau": 0.0, "xdr": 0.0, "xlm": 0.0, "xrp": 0.0, "yfi": 0.0, "zar": 0.0, "bits": 0.0, "link": 0.0, "sats": 0.0}, "total_supply": 10000000.0, "max_supply": null, "circulating_supply": 0.0, "last_updated": "2021-05-21T06:16:40.364Z"}, "community_data": {"facebook_likes": null, "twitter_followers": 1492, "reddit_average_posts_48h": 0.0, "reddit_average_comments_48h": 0.0, "reddit_subscribers": 0, "reddit_accounts_active_48h": 0, "telegram_channel_user_count": 524}, "developer_data": {"forks": 0, "stars": 0, "subscribers": 0, "total_issues": 0, "closed_issues": 0, "pull_requests_merged": 0, "pull_request_contributors": 0, "code_additions_deletions_4_weeks": {"additions": null, "deletions": null}, "commit_count_4_weeks": 0, "last_4_weeks_commit_activity_series": []}, "public_interest_stats": {"alexa_rank": 4181676, "bing_matches": null}, "status_updates": [], "last_updated": "2021-05-21T06:16:40.364Z", "tickers": [{"base": "0XA9EA4B786EE5B7A733C035564BFD9341A4C9FC1E", "target": "WBNB", "market": {"name": "PancakeSwap (v2)", "identifier": "pancakeswap", "has_trading_incentive": false}, "last": 0.000215197893092532, "volume": 47760.4872402585, "converted_last": {"btc": 2.08e-06, "eth": 3.022e-05, "usd": 0.084346}, "converted_volume": {"btc": 0.09911033, "eth": 1.443174, "usd": 4028.41}, "trust_score": null, "bid_ask_spread_percentage": null, "timestamp": "2021-05-21T04:06:27+00:00", "last_traded_at": "2021-05-21T04:06:27+00:00", "last_fetch_at": "2021-05-21T04:06:27+00:00", "is_anomaly": false, "is_stale": false, "trade_url": "https://exchange.pancakeswap.finance/#/swap?outputCurrency=0xa9ea4b786ee5b7a733c035564bfd9341a4c9fc1e", "token_info_url": null, "coin_id": "apecoin", "target_coin_id": "wbnb"}]}