{"id": "geysercoin", "symbol": "gsr", "name": "GeyserCoin", "asset_platform_id": null, "platforms": {"": ""}, "block_time_in_minutes": 0, "hashing_algorithm": "Scrypt", "categories": [], "public_notice": "YoBit is trading GeyserCoin's old chain. More info: https://twitter.com/GeyserCoin_Dev/status/954889592687165446", "additional_notices": [], "localization": {"en": "GeyserCoin", "de": "GeyserCoin", "es": "GeyserCoin", "fr": "GeyserCoin", "it": "GeyserCoin", "pl": "GeyserCoin", "ro": "GeyserCoin", "hu": "GeyserCoin", "nl": "GeyserCoin", "pt": "GeyserCoin", "sv": "GeyserCoin", "vi": "GeyserCoin", "tr": "GeyserCoin", "ru": "GeyserCoin", "ja": "GeyserCoin", "zh": "GeyserCoin", "zh-tw": "GeyserCoin", "ko": "GeyserCoin", "ar": "GeyserCoin", "th": "GeyserCoin", "id": "GeyserCoin"}, "description": {"en": "GeyserCoin is a currency that is not dependent on the present banking system and has its own independent value. ", "de": "GeyserCoin is a currency that is not dependent on the present banking system and has its own independent value. ", "es": "GeyserCoin is a currency that is not dependent on the present banking system and has its own independent value. ", "fr": "GeyserCoin is a currency that is not dependent on the present banking system and has its own independent value. ", "it": "GeyserCoin is a currency that is not dependent on the present banking system and has its own independent value. ", "pl": "GeyserCoin is a currency that is not dependent on the present banking system and has its own independent value. ", "ro": "GeyserCoin is a currency that is not dependent on the present banking system and has its own independent value. ", "hu": "GeyserCoin is a currency that is not dependent on the present banking system and has its own independent value. ", "nl": "GeyserCoin is a currency that is not dependent on the present banking system and has its own independent value. ", "pt": "GeyserCoin is a currency that is not dependent on the present banking system and has its own independent value. ", "sv": "GeyserCoin is a currency that is not dependent on the present banking system and has its own independent value. ", "vi": "GeyserCoin is a currency that is not dependent on the present banking system and has its own independent value. ", "tr": "GeyserCoin is a currency that is not dependent on the present banking system and has its own independent value. ", "ru": "GeyserCoin is a currency that is not dependent on the present banking system and has its own independent value. ", "ja": "GeyserCoin is a currency that is not dependent on the present banking system and has its own independent value. ", "zh": "GeyserCoin is a currency that is not dependent on the present banking system and has its own independent value. ", "zh-tw": "GeyserCoin is a currency that is not dependent on the present banking system and has its own independent value. ", "ko": "GeyserCoin is a currency that is not dependent on the present banking system and has its own independent value. ", "ar": "GeyserCoin is a currency that is not dependent on the present banking system and has its own independent value. ", "th": "GeyserCoin is a currency that is not dependent on the present banking system and has its own independent value. ", "id": "GeyserCoin is a currency that is not dependent on the present banking system and has its own independent value. "}, "links": {"homepage": ["http://geysercoin.com/", "", ""], "blockchain_site": ["http://geysercoin.com:3001/", "", "", "", ""], "official_forum_url": ["", "", ""], "chat_url": ["", "", ""], "announcement_url": ["", ""], "twitter_screen_name": "GeyserCoin_Dev", "facebook_username": "", "bitcointalk_thread_identifier": 1949336, "telegram_channel_identifier": "", "subreddit_url": null, "repos_url": {"github": ["https://github.com/geysercoin/geysercoin"], "bitbucket": []}}, "image": {"thumb": "https://assets.coingecko.com/coins/images/816/thumb/geysercoin.png?1548127012", "small": "https://assets.coingecko.com/coins/images/816/small/geysercoin.png?1548127012", "large": "https://assets.coingecko.com/coins/images/816/large/geysercoin.png?1548127012"}, "country_origin": "", "genesis_date": null, "sentiment_votes_up_percentage": null, "sentiment_votes_down_percentage": null, "market_cap_rank": 2514, "coingecko_rank": 2530, "coingecko_score": 12.395, "developer_score": 17.14, "community_score": 0.0, "liquidity_score": 1.0, "public_interest_score": 0.0, "market_data": {"current_price": {"aed": 0.119447, "ars": 3.06, "aud": 0.04192178, "bch": 3.982e-05, "bdt": 2.76, "bhd": 0.01225899, "bmd": 0.0325185, "bnb": 8.301e-05, "brl": 0.171779, "btc": 8e-07, "cad": 0.03927201, "chf": 0.02917105, "clp": 23.45, "cny": 0.209227, "czk": 0.678154, "dkk": 0.197694, "dot": 0.00112798, "eos": 0.00498052, "eth": 1.165e-05, "eur": 0.02658436, "gbp": 0.02293709, "hkd": 0.252448, "huf": 9.29, "idr": 467.25, "ils": 0.105917, "inr": 2.37, "jpy": 3.54, "krw": 36.66, "kwd": 0.00977926, "lkr": 6.4, "ltc": 0.00015733, "mmk": 53.5, "mxn": 0.647673, "myr": 0.134757, "ngn": 13.41, "nok": 0.270262, "nzd": 0.04525018, "php": 1.56, "pkr": 4.99, "pln": 0.119494, "rub": 2.39, "sar": 0.121955, "sek": 0.270086, "sgd": 0.04329513, "thb": 1.02, "try": 0.27277, "twd": 0.910794, "uah": 0.893004, "usd": 0.0325185, "vef": 0.00325608, "vnd": 747.19, "xag": 0.00117294, "xau": 1.735e-05, "xdr": 0.02252878, "xlm": 0.06675432, "xrp": 0.02832915, "yfi": 6.316e-07, "zar": 0.455259, "bits": 0.8, "link": 0.00107339, "sats": 80.0}, "total_value_locked": null, "mcap_to_tvl_ratio": null, "fdv_to_tvl_ratio": null, "roi": null, "ath": {"aed": 3.94, "ars": 40.98, "aud": 1.53, "bch": 0.00232994, "bdt": 89.63, "bhd": 0.404426, "bmd": 1.07, "bnb": 2.711017, "brl": 4.37, "btc": 0.00016759, "cad": 1.5, "chf": 1.14, "clp": 715.46, "cny": 7.44, "czk": 23.25, "dkk": 7.38, "dot": 0.00555133, "eos": 0.08295159, "eth": 0.00466698, "eur": 0.991612, "gbp": 0.866318, "hkd": 9.08, "huf": 294.54, "idr": 16083.88, "ils": 3.83, "inr": 77.56, "jpy": 126.93, "krw": 1238.99, "kwd": 0.324573, "lkr": 180.6, "ltc": 0.01844184, "mmk": 1721.5, "mxn": 23.09, "myr": 4.6, "ngn": 19.48, "nok": 8.73, "nzd": 1.66, "php": 60.89, "pkr": 132.72, "pln": 4.26, "rub": 72.04, "sar": 4.02, "sek": 10.2, "sgd": 1.55, "thb": 34.76, "try": 6.73, "twd": 34.51, "uah": 27.38, "usd": 1.16, "vef": 266515, "vnd": 23544, "xag": 0.074601, "xau": 0.00089546, "xdr": 0.816779, "xlm": 3.975788, "xrp": 1.305057, "yfi": 1.94e-06, "zar": 15.34, "bits": 0.903694, "link": 0.0020298, "sats": 90.37}, "ath_change_percentage": {"aed": -96.96826, "ars": -92.52188, "aud": -97.25514, "bch": -98.29114, "bdt": -96.92495, "bhd": -96.9688, "bmd": -96.9683, "bnb": -99.99694, "brl": -96.0723, "btc": -99.52264, "cad": -97.38038, "chf": -97.45191, "clp": -96.72207, "cny": -97.1882, "czk": -97.08377, "dkk": -97.32178, "dot": -79.68088, "eos": -93.99587, "eth": -99.75039, "eur": -97.31908, "gbp": -97.35235, "hkd": -97.22107, "huf": -96.84605, "idr": -97.09489, "ils": -97.23778, "inr": -96.93837, "jpy": -97.21116, "krw": -97.04089, "kwd": -96.98704, "lkr": -96.45441, "ltc": -99.1469, "mmk": -96.89219, "mxn": -97.1945, "myr": -97.0736, "ngn": -31.14705, "nok": -96.90588, "nzd": -97.26789, "php": -97.44198, "pkr": -96.24176, "pln": -97.19814, "rub": -96.6813, "sar": -96.96855, "sek": -97.35272, "sgd": -97.20429, "thb": -97.06404, "try": -95.94769, "twd": -97.3608, "uah": -96.73792, "usd": -97.19152, "vef": -100.0, "vnd": -96.82642, "xag": -98.42773, "xau": -98.06275, "xdr": -97.24175, "xlm": -98.32098, "xrp": -97.82928, "yfi": -67.46165, "zar": -97.03312, "bits": -11.47448, "link": -47.11863, "sats": -11.47448}, "ath_date": {"aed": "2018-09-21T08:20:46.821Z", "ars": "2018-09-21T08:20:46.821Z", "aud": "2018-06-04T00:45:15.134Z", "bch": "2018-09-20T07:35:53.682Z", "bdt": "2018-09-21T08:20:46.821Z", "bhd": "2018-09-21T08:20:46.821Z", "bmd": "2018-09-21T08:20:46.821Z", "bnb": "2017-10-22T00:00:00.000Z", "brl": "2018-09-21T08:20:46.821Z", "btc": "2018-06-24T07:22:59.491Z", "cad": "2018-06-04T00:35:17.507Z", "chf": "2018-06-04T00:45:15.134Z", "clp": "2018-09-21T08:20:46.821Z", "cny": "2018-06-04T00:35:17.507Z", "czk": "2018-09-21T08:20:46.821Z", "dkk": "2018-06-04T00:35:17.507Z", "dot": "2020-09-11T19:12:08.653Z", "eos": "2019-05-22T22:46:38.965Z", "eth": "2018-09-20T00:00:00.000Z", "eur": "2018-06-04T00:35:17.507Z", "gbp": "2018-06-04T00:35:17.507Z", "hkd": "2018-06-04T00:35:17.507Z", "huf": "2018-09-21T08:20:46.821Z", "idr": "2018-06-04T00:35:17.507Z", "ils": "2018-09-21T08:20:46.821Z", "inr": "2018-06-04T00:45:15.134Z", "jpy": "2018-06-04T00:35:17.507Z", "krw": "2018-06-04T00:45:15.134Z", "kwd": "2018-09-21T08:20:46.821Z", "lkr": "2018-09-21T08:20:46.821Z", "ltc": "2018-09-20T08:25:23.618Z", "mmk": "2018-09-21T08:20:46.821Z", "mxn": "2018-06-04T00:35:17.507Z", "myr": "2018-06-04T00:35:17.507Z", "ngn": "2021-03-12T17:54:05.123Z", "nok": "2018-09-21T08:20:46.821Z", "nzd": "2018-06-04T00:35:17.507Z", "php": "2018-06-04T00:45:15.134Z", "pkr": "2018-09-21T08:20:46.821Z", "pln": "2018-06-04T00:35:17.507Z", "rub": "2018-06-04T00:35:17.507Z", "sar": "2018-09-21T08:20:46.821Z", "sek": "2018-06-04T00:35:17.507Z", "sgd": "2018-06-04T00:45:15.134Z", "thb": "2018-09-21T08:20:46.821Z", "try": "2018-09-21T08:20:46.821Z", "twd": "2018-06-04T00:45:15.134Z", "uah": "2018-09-20T00:00:00.000Z", "usd": "2018-06-04T00:35:17.507Z", "vef": "2018-09-21T08:20:46.821Z", "vnd": "2018-06-04T00:00:00.000Z", "xag": "2018-09-21T08:20:46.821Z", "xau": "2018-06-04T00:35:17.507Z", "xdr": "2018-06-04T00:35:17.507Z", "xlm": "2019-05-22T22:57:03.765Z", "xrp": "2019-05-22T22:46:38.965Z", "yfi": "2020-11-03T12:54:22.065Z", "zar": "2018-09-21T11:15:52.151Z", "bits": "2021-02-19T22:52:33.134Z", "link": "2020-09-19T03:49:30.509Z", "sats": "2021-02-19T22:52:33.134Z"}, "atl": {"aed": 0.00823682, "ars": 0.04527655, "aud": 0.00291866, "bch": 2.03e-06, "bdt": 0.186172, "bhd": 0.00084566, "bmd": 0.00224252, "bnb": 2.738e-05, "brl": 0.00740817, "btc": 1.765e-07, "cad": 0.00289129, "chf": 0.00214067, "clp": 1.36, "cny": 0.01409, "czk": 0.04626013, "dkk": 0.01357386, "dot": 0.00034586, "eos": 0.0018339, "eth": 5.4e-06, "eur": 0.0018211, "gbp": 0.00159758, "hkd": 0.01760123, "huf": 0.570229, "idr": 30.85, "ils": 0.00790613, "inr": 0.146034, "jpy": 0.238366, "krw": 2.38, "kwd": 0.00067208, "lkr": 0.348107, "ltc": 1.827e-05, "mmk": 3.0, "mxn": 0.04081214, "myr": 0.00866392, "ngn": 2.43, "nok": 0.01770248, "nzd": 0.00309999, "php": 0.117195, "pkr": 0.259516, "pln": 0.00767369, "rub": 0.128559, "sar": 0.00841148, "sek": 0.018728, "sgd": 0.00294063, "thb": 0.070044, "try": 0.00892527, "twd": 0.065009, "uah": 0.059447, "usd": 0.00224252, "vef": 0.00073004, "vnd": 51.12, "xag": 0.00013666, "xau": 1.69e-06, "xdr": 0.00154246, "xlm": 0.02424913, "xrp": 0.00957562, "yfi": 1.963e-07, "zar": 0.02655528, "bits": 0.17652, "link": 0.00039373, "sats": 17.65}, "atl_change_percentage": {"aed": 1350.15841, "ars": 6668.45039, "aud": 1336.33736, "bch": 1857.74071, "bdt": 1380.44105, "bhd": 1349.64276, "bmd": 1350.08498, "bnb": 203.21493, "brl": 2218.77757, "btc": 353.20725, "cad": 1258.28546, "chf": 1262.70597, "clp": 1626.88295, "cny": 1384.93447, "czk": 1365.95756, "dkk": 1356.43087, "dot": 226.13943, "eos": 171.58035, "eth": 115.85221, "eur": 1359.79893, "gbp": 1335.73888, "hkd": 1334.26103, "huf": 1529.08205, "idr": 1414.54631, "ils": 1239.68183, "inr": 1526.14633, "jpy": 1385.08872, "krw": 1439.51708, "kwd": 1355.06375, "lkr": 1739.43508, "ltc": 761.11688, "mmk": 1685.25616, "mxn": 1486.96061, "myr": 1455.37815, "ngn": 452.8518, "nok": 1426.68984, "nzd": 1359.6874, "php": 1229.11308, "pkr": 1822.01719, "pln": 1457.18633, "rub": 1759.75776, "sar": 1349.86925, "sek": 1342.15208, "sgd": 1372.31007, "thb": 1356.83992, "try": 2956.15571, "twd": 1301.0212, "uah": 1402.17398, "usd": 1350.08498, "vef": 346.01264, "vnd": 1361.6813, "xag": 758.26071, "xau": 926.53016, "xdr": 1360.57762, "xlm": 175.28537, "xrp": 195.8466, "yfi": 221.69488, "zar": 1614.38391, "bits": 353.20725, "link": 172.62147, "sats": 353.20725}, "atl_date": {"aed": "2018-04-02T00:00:00.000Z", "ars": "2018-04-02T00:00:00.000Z", "aud": "2018-04-02T00:00:00.000Z", "bch": "2018-04-24T00:00:00.000Z", "bdt": "2018-04-02T00:00:00.000Z", "bhd": "2018-04-02T00:00:00.000Z", "bmd": "2018-04-02T00:00:00.000Z", "bnb": "2021-05-04T08:18:02.255Z", "brl": "2018-04-02T00:00:00.000Z", "btc": "2021-01-08T14:57:08.305Z", "cad": "2018-04-02T00:00:00.000Z", "chf": "2018-04-02T00:00:00.000Z", "clp": "2018-04-02T00:00:00.000Z", "cny": "2018-04-02T00:00:00.000Z", "czk": "2018-04-02T00:00:00.000Z", "dkk": "2018-04-02T00:00:00.000Z", "dot": "2021-03-12T21:39:08.533Z", "eos": "2020-03-22T09:39:43.017Z", "eth": "2021-05-04T08:18:02.255Z", "eur": "2018-04-02T00:00:00.000Z", "gbp": "2018-04-02T00:00:00.000Z", "hkd": "2018-04-02T00:00:00.000Z", "huf": "2018-04-02T00:00:00.000Z", "idr": "2018-04-02T00:00:00.000Z", "ils": "2018-04-02T00:00:00.000Z", "inr": "2018-04-02T00:00:00.000Z", "jpy": "2018-04-02T00:00:00.000Z", "krw": "2018-04-02T00:00:00.000Z", "kwd": "2018-04-02T00:00:00.000Z", "lkr": "2018-04-02T00:00:00.000Z", "ltc": "2018-04-04T00:00:00.000Z", "mmk": "2018-04-02T00:00:00.000Z", "mxn": "2018-04-02T00:00:00.000Z", "myr": "2018-04-02T00:00:00.000Z", "ngn": "2020-12-25T23:10:05.026Z", "nok": "2018-04-02T00:00:00.000Z", "nzd": "2018-04-02T00:00:00.000Z", "php": "2018-04-02T00:00:00.000Z", "pkr": "2018-04-02T00:00:00.000Z", "pln": "2018-04-02T00:00:00.000Z", "rub": "2018-04-02T00:00:00.000Z", "sar": "2018-04-02T00:00:00.000Z", "sek": "2018-04-02T00:00:00.000Z", "sgd": "2018-04-02T00:00:00.000Z", "thb": "2018-04-02T00:00:00.000Z", "try": "2018-04-02T00:00:00.000Z", "twd": "2018-04-02T00:00:00.000Z", "uah": "2018-04-02T00:00:00.000Z", "usd": "2018-04-02T00:00:00.000Z", "vef": "2021-01-08T14:57:08.305Z", "vnd": "2018-04-02T00:00:00.000Z", "xag": "2018-04-02T00:00:00.000Z", "xau": "2018-04-02T00:00:00.000Z", "xdr": "2018-04-02T00:00:00.000Z", "xlm": "2021-01-08T14:57:08.305Z", "xrp": "2021-04-15T19:01:15.993Z", "yfi": "2021-01-08T14:57:08.305Z", "zar": "2018-04-02T00:00:00.000Z", "bits": "2021-01-08T14:57:08.305Z", "link": "2021-04-15T19:01:15.993Z", "sats": "2021-01-08T14:57:08.305Z"}, "market_cap": {"aed": 179889, "ars": 4615204, "aud": 63135, "bch": 59.963, "bdt": 4150815, "bhd": 18462.18, "bmd": 48973, "bnb": 125.007, "brl": 258701, "btc": 1.204809, "cad": 59144, "chf": 43932, "clp": 35319468, "cny": 315099, "czk": 1021308, "dkk": 297729, "dot": 1699, "eos": 7501, "eth": 17.543575, "eur": 40036, "gbp": 34544, "hkd": 380189, "huf": 13990091, "idr": 703690333, "ils": 159512, "inr": 3576369, "jpy": 5331202, "krw": 55215124, "kwd": 14727.67, "lkr": 9643296, "ltc": 236.936, "mmk": 80572986, "mxn": 975402, "myr": 202945, "ngn": 20201462, "nok": 407018, "nzd": 68147, "php": 2345843, "pkr": 7511894, "pln": 179959, "rub": 3600713, "sar": 183666, "sek": 406753, "sgd": 65203, "thb": 1536780, "try": 410795, "twd": 1371667, "uah": 1344874, "usd": 48973, "vef": 4903.69, "vnd": 1125273994, "xag": 1766.46, "xau": 26.13, "xdr": 33929, "xlm": 100533, "xrp": 42664, "yfi": 0.95123045, "zar": 685626, "bits": 1204809, "link": 1617, "sats": 120480932}, "market_cap_rank": 2514, "fully_diluted_valuation": {}, "total_volume": {"aed": 6.92, "ars": 177.63, "aud": 2.43, "bch": 0.00230782, "bdt": 159.76, "bhd": 0.710568, "bmd": 1.88, "bnb": 0.00481124, "brl": 9.96, "btc": 4.637e-05, "cad": 2.28, "chf": 1.69, "clp": 1359.37, "cny": 12.13, "czk": 39.31, "dkk": 11.46, "dot": 0.06538128, "eos": 0.28868601, "eth": 0.00067521, "eur": 1.54, "gbp": 1.33, "hkd": 14.63, "huf": 538.45, "idr": 27083, "ils": 6.14, "inr": 137.65, "jpy": 205.19, "krw": 2125.11, "kwd": 0.566835, "lkr": 371.15, "ltc": 0.00911915, "mmk": 3101.07, "mxn": 37.54, "myr": 7.81, "ngn": 777.51, "nok": 15.67, "nzd": 2.62, "php": 90.29, "pkr": 289.12, "pln": 6.93, "rub": 138.58, "sar": 7.07, "sek": 15.66, "sgd": 2.51, "thb": 59.15, "try": 15.81, "twd": 52.79, "uah": 51.76, "usd": 1.88, "vef": 0.188732, "vnd": 43309, "xag": 0.067987, "xau": 0.0010055, "xdr": 1.31, "xlm": 3.869283, "xrp": 1.642043, "yfi": 3.661e-05, "zar": 26.39, "bits": 46.37, "link": 0.06221681, "sats": 4637.04}, "high_24h": {"aed": 0.12184, "ars": 3.13, "aud": 0.04275919, "bch": 4.117e-05, "bdt": 2.81, "bhd": 0.01250403, "bmd": 0.03317008, "bnb": 8.98e-05, "brl": 0.175221, "btc": 8.2e-07, "cad": 0.04006116, "chf": 0.02975933, "clp": 23.92, "cny": 0.213393, "czk": 0.69176, "dkk": 0.201677, "dot": 0.00115524, "eos": 0.00515747, "eth": 1.216e-05, "eur": 0.02712035, "gbp": 0.02340007, "hkd": 0.257471, "huf": 9.47, "idr": 476.52, "ils": 0.108039, "inr": 2.42, "jpy": 3.61, "krw": 37.38, "kwd": 0.00997511, "lkr": 6.53, "ltc": 0.00015658, "mmk": 54.57, "mxn": 0.660535, "myr": 0.137394, "ngn": 13.68, "nok": 0.2757, "nzd": 0.04617312, "php": 1.59, "pkr": 5.09, "pln": 0.121922, "rub": 2.44, "sar": 0.124389, "sek": 0.275591, "sgd": 0.0441519, "thb": 1.04, "try": 0.278322, "twd": 0.925206, "uah": 0.910897, "usd": 0.03317008, "vef": 0.00332132, "vnd": 762.33, "xag": 0.00119797, "xau": 1.772e-05, "xdr": 0.02298322, "xlm": 0.06788525, "xrp": 0.02810234, "yfi": 6.431e-07, "zar": 0.464222, "bits": 0.82, "link": 0.00110808, "sats": 82.0}, "low_24h": {"aed": 0.116354, "ars": 2.99, "aud": 0.04077903, "bch": 3.793e-05, "bdt": 2.68, "bhd": 0.01194181, "bmd": 0.03167833, "bnb": 7.844e-05, "brl": 0.167417, "btc": 7.7e-07, "cad": 0.03821299, "chf": 0.02846598, "clp": 22.8, "cny": 0.20385, "czk": 0.661253, "dkk": 0.192784, "dot": 0.00105631, "eos": 0.0047227, "eth": 1.092e-05, "eur": 0.02592519, "gbp": 0.0223298, "hkd": 0.245933, "huf": 9.06, "idr": 455.47, "ils": 0.10318, "inr": 2.31, "jpy": 3.45, "krw": 35.76, "kwd": 0.00952602, "lkr": 6.24, "ltc": 0.00014761, "mmk": 52.12, "mxn": 0.630542, "myr": 0.131259, "ngn": 13.08, "nok": 0.263487, "nzd": 0.04402435, "php": 1.51, "pkr": 4.86, "pln": 0.116484, "rub": 2.33, "sar": 0.1188, "sek": 0.263069, "sgd": 0.04218017, "thb": 0.993749, "try": 0.26555, "twd": 0.885796, "uah": 0.869932, "usd": 0.03167833, "vef": 0.00317195, "vnd": 728.72, "xag": 0.00113891, "xau": 1.688e-05, "xdr": 0.02194959, "xlm": 0.06212081, "xrp": 0.02598529, "yfi": 5.856e-07, "zar": 0.44273, "bits": 0.77, "link": 0.00100112, "sats": 77.0}, "price_change_24h": -0.00037109, "price_change_percentage_24h": -1.12829, "price_change_percentage_7d": 3.94135, "price_change_percentage_14d": -7.82924, "price_change_percentage_30d": 31.88067, "price_change_percentage_60d": 24.36818, "price_change_percentage_200d": 68.89182, "price_change_percentage_1y": -11.66067, "market_cap_change_24h": -523.43787581, "market_cap_change_percentage_24h": -1.05752, "price_change_24h_in_currency": {"aed": -0.00135599, "ars": -0.03373145, "aud": -0.00046991, "bch": 8.14e-08, "bdt": -0.03340595, "bhd": -0.0001393, "bmd": -0.00037109, "bnb": -3.9049e-06, "brl": -0.00286807, "btc": -1e-08, "cad": -0.00053348, "chf": -0.00049, "clp": -0.06703546, "cny": -0.00256195, "czk": -0.00900047, "dkk": -0.00285303, "dot": -2.4436e-06, "eos": -8.36589e-05, "eth": -1.749e-07, "eur": -0.0003857, "gbp": -0.00032789, "hkd": -0.00290043, "huf": -0.14478866, "idr": -6.10988766, "ils": -0.00120442, "inr": -0.03017483, "jpy": -0.04539591, "krw": -0.57217872, "kwd": -0.00011232, "lkr": -0.07766683, "ltc": 6.03e-06, "mmk": -0.64887161, "mxn": -0.00635371, "myr": -0.00150491, "ngn": -0.15307516, "nok": -0.00232374, "nzd": -0.00046425, "php": -0.01840385, "pkr": -0.05084318, "pln": -0.00232693, "rub": -0.02973114, "sar": -0.00139669, "sek": -0.00383008, "sgd": -0.00053367, "thb": -0.01175996, "try": -0.00227912, "twd": -0.00886441, "uah": -0.00961835, "usd": -0.00037109, "vef": -3.716e-05, "vnd": -11.57583693, "xag": -9.19e-06, "xau": -2e-07, "xdr": -0.00025495, "xlm": 0.00081779, "xrp": 0.00105961, "yfi": 1.46e-08, "zar": -0.00774903, "bits": -0.01, "link": -3.8542e-06, "sats": -1.0}, "price_change_percentage_1h_in_currency": {}, "price_change_percentage_24h_in_currency": {"aed": -1.12248, "ars": -1.08873, "aud": -1.1085, "bch": 0.20474, "bdt": -1.19753, "bhd": -1.12357, "bmd": -1.12829, "bnb": -4.49305, "brl": -1.64221, "btc": -1.23457, "cad": -1.34021, "chf": -1.65201, "clp": -0.28502, "cny": -1.20967, "czk": -1.30982, "dkk": -1.42263, "dot": -0.21617, "eos": -1.65197, "eth": -1.47881, "eur": -1.43009, "gbp": -1.40938, "hkd": -1.13587, "huf": -1.53471, "idr": -1.29074, "ils": -1.12435, "inr": -1.25472, "jpy": -1.26615, "krw": -1.53666, "kwd": -1.13553, "lkr": -1.1984, "ltc": 3.98702, "mmk": -1.19829, "mxn": -0.97148, "myr": -1.10443, "ngn": -1.12829, "nok": -0.85248, "nzd": -1.01555, "php": -1.16772, "pkr": -1.00904, "pln": -1.91013, "rub": -1.22824, "sar": -1.13227, "sek": -1.39827, "sgd": -1.21762, "thb": -1.13932, "try": -0.82862, "twd": -0.96388, "uah": -1.0656, "usd": -1.12829, "vef": -1.12829, "vnd": -1.52562, "xag": -0.77701, "xau": -1.13756, "xdr": -1.11902, "xlm": 1.24026, "xrp": 3.8857, "yfi": 2.36179, "zar": -1.67363, "bits": -1.23457, "link": -0.35779, "sats": -1.23457}, "price_change_percentage_7d_in_currency": {"aed": 3.94588, "ars": 4.17592, "aud": 3.55978, "bch": 55.38773, "bdt": 3.97165, "bhd": 3.93087, "bmd": 3.94135, "bnb": 49.67832, "brl": 3.42445, "btc": 26.98413, "cad": 3.19173, "chf": 2.95707, "clp": 5.92387, "cny": 3.65298, "czk": 2.68769, "dkk": 2.65177, "dot": 44.54029, "eos": 62.6443, "eth": 40.03891, "eur": 2.64919, "gbp": 3.03524, "hkd": 3.87779, "huf": 0.50987, "idr": 4.36315, "ils": 3.00934, "inr": 3.35232, "jpy": 3.38576, "krw": 3.99173, "kwd": 3.83397, "lkr": 3.91553, "ltc": 54.83531, "mmk": 9.82045, "mxn": 3.76531, "myr": 4.40745, "ngn": 4.92273, "nok": 3.38165, "nzd": 3.9026, "php": 4.20862, "pkr": 4.86979, "pln": 1.90855, "rub": 3.20386, "sar": 3.94066, "sek": 2.70846, "sgd": 3.7691, "thb": 4.0213, "try": 2.5379, "twd": 4.13654, "uah": 3.31966, "usd": 3.94135, "vef": 3.94135, "vnd": 3.71407, "xag": 1.55693, "xau": 1.29255, "xdr": 3.43121, "xlm": 36.3978, "xrp": 18.39373, "yfi": 32.92322, "zar": 2.91721, "bits": 26.98413, "link": 45.6207, "sats": 26.98413}, "price_change_percentage_14d_in_currency": {"aed": -7.82924, "ars": -7.38652, "aud": -7.47441, "bch": 71.26047, "bdt": -7.87879, "bhd": -7.82656, "bmd": -7.82924, "bnb": 49.54564, "brl": -7.7297, "btc": 28.26566, "cad": -8.43127, "chf": -8.91699, "clp": -5.06493, "cny": -8.25843, "czk": -9.80998, "dkk": -9.08428, "dot": 33.67435, "eos": 59.60683, "eth": 15.72401, "eur": -9.08677, "gbp": -9.66036, "hkd": -7.89139, "huf": -11.34354, "idr": -7.05937, "ils": -7.9183, "inr": -8.56601, "jpy": -7.99342, "krw": -7.25643, "kwd": -8.02834, "lkr": -7.87963, "ltc": 58.57001, "mmk": -2.64525, "mxn": -8.68272, "myr": -7.33731, "ngn": -3.7194, "nok": -7.76306, "nzd": -7.24419, "php": -7.93059, "pkr": -7.7765, "pln": -10.59223, "rub": -8.68509, "sar": -7.84758, "sek": -9.13541, "sgd": -7.96749, "thb": -7.38803, "try": -6.72836, "twd": -7.52516, "uah": -8.72353, "usd": -7.82924, "vef": -7.82924, "vnd": -8.0096, "xag": -9.26464, "xau": -10.78275, "xdr": -8.51381, "xlm": 23.99024, "xrp": 29.41588, "yfi": -5.46907, "zar": -9.05688, "bits": 28.26566, "link": 43.98619, "sats": 28.26566}, "price_change_percentage_30d_in_currency": {"aed": 31.88067, "ars": 33.84853, "aud": 32.25954, "bch": 51.93054, "bdt": 31.60742, "bhd": 32.00848, "bmd": 31.88067, "bnb": 75.79232, "brl": 25.06454, "btc": 81.85068, "cad": 27.16871, "chf": 29.26019, "clp": 35.60343, "cny": 30.58981, "czk": 27.94338, "dkk": 29.92258, "dot": 55.14964, "eos": 33.21283, "eth": 3.04258, "eur": 29.92366, "gbp": 29.89963, "hkd": 31.88491, "huf": 25.71497, "idr": 30.43079, "ils": 32.1567, "inr": 28.17404, "jpy": 32.43542, "krw": 33.43297, "kwd": 31.69674, "lkr": 34.11158, "ltc": 63.0077, "mmk": 53.54333, "mxn": 32.04041, "myr": 32.79395, "ngn": 32.51596, "nok": 32.12804, "nzd": 32.14752, "php": 30.77356, "pkr": 31.98899, "pln": 28.27958, "rub": 26.62173, "sar": 31.87736, "sek": 30.31783, "sgd": 32.18845, "thb": 32.35016, "try": 36.37353, "twd": 31.37409, "uah": 29.30238, "usd": 31.88067, "vef": 31.88067, "vnd": 31.34983, "xag": 23.04544, "xau": 24.52751, "xdr": 30.86405, "xlm": 35.53029, "xrp": 50.06257, "yfi": 23.86871, "zar": 29.1409, "bits": 81.85068, "link": 62.48607, "sats": 81.85068}, "price_change_percentage_60d_in_currency": {"aed": 24.37596, "ars": 28.21471, "aud": 23.88404, "bch": -19.41485, "bdt": 24.57477, "bhd": 24.35564, "bmd": 24.36818, "bnb": -15.23457, "brl": 19.66932, "btc": 77.77778, "cad": 19.9299, "chf": 20.03477, "clp": 25.74549, "cny": 22.93705, "czk": 18.17318, "dkk": 20.86891, "dot": 60.7239, "eos": -20.12913, "eth": -19.41329, "eur": 20.86328, "gbp": 21.45793, "hkd": 24.33791, "huf": 14.83187, "idr": 24.01442, "ils": 22.71898, "inr": 25.37151, "jpy": 24.4382, "krw": 24.15496, "kwd": 23.8784, "lkr": 24.04581, "ltc": 19.10447, "mmk": 45.17575, "mxn": 19.10461, "myr": 25.47334, "ngn": 29.73288, "nok": 20.66203, "nzd": 23.75762, "php": 22.64578, "pkr": 22.4703, "pln": 17.53832, "rub": 23.20199, "sar": 24.35465, "sek": 20.83778, "sgd": 23.22102, "thb": 26.56346, "try": 23.74966, "twd": 22.66452, "uah": 23.20846, "usd": 24.36818, "vef": 24.36818, "vnd": 23.73854, "xag": 17.25346, "xau": 15.66501, "xdr": 23.12889, "xlm": 4.11289, "xrp": -44.46143, "yfi": -13.2272, "zar": 16.69324, "bits": 77.77778, "link": 21.82139, "sats": 77.77778}, "price_change_percentage_200d_in_currency": {"aed": 68.90226, "ars": 103.20004, "aud": 52.91891, "bch": -44.69356, "bdt": 68.68334, "bhd": 68.86943, "bmd": 68.89182, "bnb": -87.83958, "brl": 55.34541, "btc": -42.85714, "cad": 53.15299, "chf": 65.30222, "clp": 57.51288, "cny": 62.37813, "czk": 50.49523, "dkk": 60.64313, "dot": -75.61256, "eos": -34.99101, "eth": -76.11696, "eur": 60.82926, "gbp": 53.94984, "hkd": 69.12493, "huf": 53.3065, "idr": 65.9213, "ils": 61.4838, "inr": 65.25198, "jpy": 75.76847, "krw": 67.52481, "kwd": 66.24716, "lkr": 80.45123, "ltc": -54.57326, "mmk": 115.93815, "mxn": 58.26072, "myr": 68.51567, "ngn": 83.10545, "nok": 47.22509, "nzd": 55.23893, "php": 66.67606, "pkr": 61.45799, "pln": 56.86274, "rub": 56.26655, "sar": 68.88921, "sek": 57.49972, "sgd": 64.71687, "thb": 70.07676, "try": 69.71707, "twd": 65.40588, "uah": 62.96517, "usd": 68.89182, "vef": -99.99993, "vnd": 67.08524, "xag": 44.10686, "xau": 69.51783, "xdr": 65.21199, "xlm": -72.93953, "xrp": -64.69356, "yfi": -64.72048, "zar": 45.39442, "bits": -42.85714, "link": -36.9993, "sats": -42.85714}, "price_change_percentage_1y_in_currency": {"aed": -11.66067, "ars": 22.5409, "aud": -24.99292, "bch": -73.99064, "bdt": -11.83144, "bhd": -11.80525, "bmd": -11.66067, "bnb": -96.17879, "brl": -18.02471, "btc": -79.27461, "cad": -23.32517, "chf": -17.90718, "clp": -20.74834, "cny": -19.87368, "czk": -26.0034, "dkk": -20.94994, "eos": -64.74029, "eth": -93.32774, "eur": -20.73806, "gbp": -23.8631, "hkd": -11.51306, "huf": -20.86335, "idr": -13.66504, "ils": -17.84183, "inr": -14.59946, "jpy": -10.65035, "krw": -18.88769, "kwd": -13.98655, "lkr": -7.02763, "ltc": -80.98639, "mmk": 3.4374, "mxn": -24.29342, "myr": -15.78602, "ngn": -6.56417, "nok": -25.84423, "nzd": -24.50559, "php": -16.27852, "pkr": -15.57527, "pln": -21.41841, "rub": -8.80567, "sar": -11.7967, "sek": -23.50666, "sgd": -16.83767, "thb": -12.93045, "try": 9.19231, "twd": -17.42033, "uah": -8.86267, "usd": -11.66067, "vef": -99.99996, "vnd": -12.60762, "xag": -44.39126, "xau": -17.69191, "xdr": -16.42202, "xlm": -87.11255, "xrp": -84.39856, "zar": -31.09659, "bits": -79.27461, "link": -88.10814, "sats": -79.27461}, "market_cap_change_24h_in_currency": {"aed": -1912.000723, "ars": -47462.39425273, "aud": -662.02869314, "bch": 0.16532192, "bdt": -47304.72451671, "bhd": -196.43728741, "bmd": -523.43787581, "bnb": -5.7872376165, "brl": -4131.21786247, "btc": -0.0141875533, "cad": -760.54088323, "chf": -706.00081124, "clp": -75620.23346651, "cny": -3630.18402966, "czk": -12814.5764085, "dkk": -4080.66552897, "dot": -2.4623672057, "eos": -120.5359437674, "eth": -0.2505939583, "eur": -551.80849985, "gbp": -468.74734217, "hkd": -4093.00344085, "huf": -207890.42932605, "idr": -8691635.91731978, "ils": -1698.47064031, "inr": -42852.98921483, "jpy": -64504.50526556, "krw": -821596.49284578, "kwd": -158.50187587, "lkr": -109985.71473424, "ltc": 9.247486, "mmk": -918875.97114415, "mxn": -8864.21259975, "myr": -2119.62987945, "ngn": -215918.12377179, "nok": -3205.9410317, "nzd": -649.9225619, "php": -26018.61949836, "pkr": -71142.45802628, "pln": -3373.1523849, "rub": -42167.85156123, "sar": -1970.54504841, "sek": -5473.07847208, "sgd": -756.49918806, "thb": -16598.71891561, "try": -3136.08312305, "twd": -12359.21269184, "uah": -13513.00302195, "usd": -523.43787581, "vef": -52.4118345, "vnd": -16615975.51961494, "xag": -12.5595999, "xau": -0.281708, "xdr": -359.41995286, "xlm": 1303, "xrp": 1625, "yfi": 0.02261242, "zar": -11171.35716576, "bits": -14187.55329789, "link": -4.6440882426, "sats": -1418755.32978864}, "market_cap_change_percentage_24h_in_currency": {"aed": -1.0517, "ars": -1.01792, "aud": -1.03772, "bch": 0.27647, "bdt": -1.12681, "bhd": -1.0528, "bmd": -1.05752, "bnb": -4.42469, "brl": -1.57181, "btc": -1.16387, "cad": -1.26959, "chf": -1.58162, "clp": -0.21365, "cny": -1.13896, "czk": -1.23917, "dkk": -1.35207, "dot": -0.14474, "eos": -1.58158, "eth": -1.40829, "eur": -1.35953, "gbp": -1.33881, "hkd": -1.0651, "huf": -1.46423, "idr": -1.22008, "ils": -1.05357, "inr": -1.18404, "jpy": -1.19548, "krw": -1.46618, "kwd": -1.06476, "lkr": -1.12768, "ltc": 4.06146, "mmk": -1.12757, "mxn": -0.90059, "myr": -1.03364, "ngn": -1.05752, "nok": -0.78151, "nzd": -0.94469, "php": -1.09697, "pkr": -0.93818, "pln": -1.83991, "rub": -1.15754, "sar": -1.0615, "sek": -1.32769, "sgd": -1.14692, "thb": -1.06856, "try": -0.75763, "twd": -0.89299, "uah": -0.99478, "usd": -1.05752, "vef": -1.05752, "vnd": -1.45513, "xag": -0.70599, "xau": -1.06679, "xdr": -1.04824, "xlm": 1.31273, "xrp": 3.96006, "yfi": 2.43506, "zar": -1.60324, "bits": -1.16387, "link": -0.28646, "sats": -1.16387}, "total_supply": 4500000.0, "max_supply": null, "circulating_supply": 1506011.64749646, "last_updated": "2021-05-21T04:05:00.491Z"}, "community_data": {"facebook_likes": null, "twitter_followers": 0, "reddit_average_posts_48h": 0.0, "reddit_average_comments_48h": 0.0, "reddit_subscribers": 0, "reddit_accounts_active_48h": 0, "telegram_channel_user_count": null}, "developer_data": {"forks": 6, "stars": 11, "subscribers": 2, "total_issues": 1, "closed_issues": 1, "pull_requests_merged": 0, "pull_request_contributors": 0, "code_additions_deletions_4_weeks": {"additions": 0, "deletions": 0}, "commit_count_4_weeks": 0, "last_4_weeks_commit_activity_series": [0, 0, 0, 0, 0, 0, 0, 0, 0, 0, 0, 0, 0, 0, 0, 0, 0, 0, 0, 0, 0, 0, 0, 0, 0, 0, 0, 0]}, "public_interest_stats": {"alexa_rank": 1760222, "bing_matches": null}, "status_updates": [], "last_updated": "2021-05-21T04:05:00.491Z", "tickers": [{"base": "GSR", "target": "BTC", "market": {"name": "CREX24", "identifier": "crex24", "has_trading_incentive": false}, "last": 8e-07, "volume": 57.96303697, "converted_last": {"btc": 8e-07, "eth": 1.162e-05, "usd": 0.03260139}, "converted_volume": {"btc": 4.637e-05, "eth": 0.0006736, "usd": 1.89}, "trust_score": "red", "bid_ask_spread_percentage": 1.234568, "timestamp": "2021-05-21T04:03:00+00:00", "last_traded_at": "2021-05-21T04:03:00+00:00", "last_fetch_at": "2021-05-21T06:26:42+00:00", "is_anomaly": false, "is_stale": false, "trade_url": "https://crex24.com/exchange/GSR-BTC", "token_info_url": null, "coin_id": "geysercoin", "target_coin_id": "bitcoin"}]}